LICENSE
MANIFEST.in
README.md
requirements.txt
setup.cfg
setup.py
notebook_autorun/__init__.py
notebook_autorun/__meta__.py
notebook_autorun/autorun.py
notebook_autorun/util.py
notebook_autorun.egg-info/PKG-INFO
notebook_autorun.egg-info/SOURCES.txt
notebook_autorun.egg-info/dependency_links.txt
notebook_autorun.egg-info/requires.txt
notebook_autorun.egg-info/top_level.txt
notebook_autorun/templates/getCellToFocus.js
notebook_autorun/templates/getCellsFromComment.js
notebook_autorun/templates/getCellsFromMetadata.js
notebook_autorun/templates/getCellsFromString.js
notebook_autorun/templates/main.template.js
notebook_autorun/templates/notice_long.md
notebook_autorun/templates/notice_safe.txt
notebook_autorun/templates/notice_short.md