Metadata-Version: 1.1
Name: notebook-autorun
Version: 0.1.7
Summary: Auto run certain cells upon notebook start - if trusted
Home-page: https://github.com/oscar6echo/notebook-autorun
Author: oscar6echo
Author-email: olivier.borderies@gmail.com
License: MIT
Download-URL: https://github.com/oscar6echo/notebook-autorun/tarball/0.1.7
Keywords: python,display,javascript
Platform: UNKNOWN
Classifier: Development Status :: 4 - Beta
Classifier: License :: OSI Approved :: MIT License
Classifier: Programming Language :: Python :: 2.7
Classifier: Programming Language :: Python :: 3.5
Classifier: Programming Language :: Python :: 3.6
